{

    "configs": [
        {
            "index": "helka-loans",
            "targets": {
                "http://purl.org/linked-data/cube#Slice": {
                    "type": "slice",
                    "indexDoc": {
                        "dataProperties": [
                            {
                                "sourceProperty": "http://data.hulib.helsinki.fi/schema/cube/year",
                                "targetProperty": "year",
                                "isFunctional": "true",
                                "type": "int"
                            }
                        ],
                        "objectProperties": [
                            {
                                "sourceProperty": "http://data.hulib.helsinki.fi/schema/cube/refRecord",
                                "targetProperty": "record",
                                "isFunctional": "true"
                            },			
                            {
                                "sourceProperty": "http://purl.org/linked-data/cube#observation",
                                "targetProperty": "obs",
                                "isFunctional": "false",
                                "nestedMapping": {
                                    "dataProperties": [
                                        {
                                            "sourceProperty": "http://data.hulib.helsinki.fi/schema/cube/month",
                                            "targetProperty": "month",
                                            "isFunctional": "true",
                                            "type": "int"
                                        },
                                        {
                                            "sourceProperty": "http://data.hulib.helsinki.fi/schema/cube/loans",
                                            "targetProperty": "loans",
                                            "isFunctional": "true",
                                            "type": "int"
                                        }															 

                                    ]													
                                }
                            }

                        ]
                    }
                }
            }
        },
        {
            "index": "mesh",

            "graph": "http://data.hulib.helsinki.fi/id/graph/mesh",
            "targets": {
                "http://www.w3.org/2004/02/skos/core#Concept": {
                    "type": "concept",
                    "idProperty": "",							
                    "indexDoc": {	
                        "multiLingualDataProperties": [
                            {
                                "sourceProperty": "http://www.w3.org/2004/02/skos/core#prefLabel",
                                "targetProperty": "prefLabel",
                                "isFunctional": "true"
                            },
                            {
                                "sourceProperty": "http://www.w3.org/2004/02/skos/core#altLabel",
                                "targetProperty": "altLabel"
                            },
                            {
                                "sourceProperty": "http://www.w3.org/2004/02/skos/core#hiddenLabel",
                                "targetProperty": "hiddenLabel"
                            }	 

                        ],
                        "objectProperties": [
                            {
                                "sourceProperty": "http://www.w3.org/2004/02/skos/core#broader",
                                "targetProperty": "broader"
                            },
                            {
                                "sourceProperty": "http://www.w3.org/2004/02/skos/core#narrower",
                                "targetProperty": "narrower"
                            }
                        ]
                    }			
                }
            }
        },

        {
            "index": "tuhat", 	 
            "graph": "http://data.hulib.helsinki.fi/id/graph/tuhat",
            "targets": {
                "http://purl.org/spar/fabio/Expression": {
                    "type": "publication",
                    "idProperty": "http://data.hulib.helsinki.fi/schemas/uhod/v1/hasCanonicalURI",			
                    "indexDoc": {		    			
                        "dataProperties": [
                            {
                                "sourceProperty": "http://purl.org/vocab/frbr/core#realizationOf->http://purl.org/dc/terms/title", 
                                "targetProperty": "title",
                                "isFunctional": "true"
                            },
                            {
                                "sourceProperty": "http://purl.org/vocab/frbr/core#realizationOf->http://purl.org/spar/fabio/hasSubTitle", 
                                "targetProperty": "subtitle",
                                "isFunctional": "true"
                            },
                            {
                                "sourceProperty": "http://prismstandard.org/namespaces/basic/2.0/publicationDate",
                                "targetProperty": "publicationDate",
                                "isFunctional": "true"
                            }		 


                        ],
                        "multiLingualDataProperties": [
                            {
                                "sourceProperty": "http://purl.org/vocab/frbr/core#realizationOf->http://purl.org/spar/fabio/hasTranslatedTitle", 
                                "targetProperty": "translatedTitle",
                                "isFunctional": "true"
                            },
                            {
                                "sourceProperty": "http://purl.org/dc/terms/abstract",
                                "targetProperty": "abstract"
                            }					 


                        ],			
                        "objectProperties": [
                            {
                                "sourceProperty": "http://data.hulib.helsinki.fi/schemas/pure/v1/publicationType",
                                "targetProperty": "publicationType",
                                "isFunctional": "true",
                                "nestedMapping": {
                                    "idProperty": "http://data.hulib.helsinki.fi/schemas/uhod/v1/hasCanonicalURI",						
                                    "multiLingualDataProperties": [
                                        {
                                            "sourceProperty": "http://www.w3.org/2004/02/skos/core#prefLabel",
                                            "targetProperty": "prefLabel",
                                            "isFunctional": "true"
                                        }						
                                    ]
                                }
                            },
                            {
                                "sourceProperty": "http://purl.org/ontology/bibo/status",
                                "targetProperty": "status",
                                "isFunctional": "true",
                                "nestedMapping": {
                                    "idProperty": "http://data.hulib.helsinki.fi/schemas/uhod/v1/hasCanonicalURI",
                                    "multiLingualDataProperties": [
                                        {
                                            "sourceProperty": "http://www.w3.org/2004/02/skos/core#prefLabel",
                                            "targetProperty": "prefLabel",
                                            "isFunctional": "true"
                                        }						
                                    ]
                                }
                            },
                            {
                                "sourceProperty": "http://purl.org/dc/terms/language",
                                "targetProperty": "language",
                                "isFunctional": "true"
                            },
                            {
                                "sourceProperty": "http://purl.org/vocab/frbr/core#partOf",
                                "targetProperty": "partOf",
                                "isFunctional": "true",
                                "nestedMapping": {							
                                    "dataProperties": [
                                        {
                                            "sourceProperty": "http://purl.org/dc/terms/title",
                                            "targetProperty": "title",
                                            "isFunctional": "true"
                                        },
                                        {
                                            "sourceProperty": "http://purl.org/spar/fabio/hasSubTitle", 
                                            "targetProperty": "subtitle",
                                            "isFunctional": "true"
                                        }
                                    ]
                                }
                            },	
                            {
                                "sourceProperty": "http://purl.org/dc/terms/publisher",
                                "targetProperty": "publisher",
                                "isFunctional": "false",
                                "nestedMapping": {
                                    "idProperty": "http://data.hulib.helsinki.fi/schemas/uhod/v1/hasCanonicalURI",
                                    "dataProperties": [
                                        {
                                            "sourceProperty": "http://purl.org/dc/terms/title",
                                            "targetProperty": "title",
                                            "isFunctional": "true"
                                        }
                                    ]
                                }
                            }				


                        ]			
                    }			
                },	

                "http://www.w3.org/2004/02/skos/core#Concept": {	
                    "type": "concept",
                    "idProperty": "http://data.hulib.helsinki.fi/schemas/uhod/v1/hasCanonicalURI",			
                    "indexDoc": {		
                        "multiLingualDataProperties": [
                            {
                                "sourceProperty": "http://www.w3.org/2004/02/skos/core#prefLabel",
                                "targetProperty": "prefLabel",
                                "isFunctional": "true"
                            },
                            {
                                "sourceProperty": "http://www.w3.org/2004/02/skos/core#altLabel",
                                "targetProperty": "altLabel"
                            },
                            {
                                "sourceProperty": "http://www.w3.org/2004/02/skos/core#hiddenLabel",
                                "targetProperty": "hiddenLabel"
                            }	 

                        ],
                        "objectProperties": [
                            {
                                "sourceProperty": "http://www.w3.org/2004/02/skos/core#broader",
                                "targetProperty": "broader"
                            },
                            {
                                "sourceProperty": "http://www.w3.org/2004/02/skos/core#narrower",
                                "targetProperty": "narrower"
                            },
                            {
                                "sourceProperty": "http://www.w3.org/2004/02/skos/core#inScheme",
                                "targetProperty": "inScheme"
                            },
                            {
                                "sourceProperty": "http://data.hulib.helsinki.fi/schemas/pure/v1/isSubjectTermOf",
                                "targetProperty": "isSubjectOf"						
                            }				
                        ]
                    },
                    "jsonDoc": {
                        "multiLingualDataProperties": [
                            {
                                "sourceProperty": "http://www.w3.org/2004/02/skos/core#prefLabel",
                                "targetProperty": "prefLabel",
                                "isFunctional": "true"
                            },
                            {
                                "sourceProperty": "http://www.w3.org/2004/02/skos/core#altLabel",
                                "targetProperty": "altLabel"
                            },
                            {
                                "sourceProperty": "http://www.w3.org/2004/02/skos/core#hiddenLabel",
                                "targetProperty": "hiddenLabel"
                            }	 

                        ],
                        "objectProperties": [
                            {
                                "sourceProperty": "http://www.w3.org/2004/02/skos/core#broader",
                                "targetProperty": "broader"
                            },
                            {
                                "sourceProperty": "http://www.w3.org/2004/02/skos/core#narrower",
                                "targetProperty": "narrower"
                            },
                            {
                                "sourceProperty": "http://www.w3.org/2004/02/skos/core#inScheme",
                                "targetProperty": "inScheme"
                            },
                            {
                                "sourceProperty": "http://data.hulib.helsinki.fi/schemas/pure/v1/isSubjectTermOf",
                                "targetProperty": "isSubjectOf",
                                "apiTemplate": "true"
                            }				
                        ]
                    }
                },

                "http://xmlns.com/foaf/0.1/Person": {
                    "type": "person",
                    "idProperty": "http://data.hulib.helsinki.fi/schemas/uhod/v1/hasCanonicalURI",			
                    "indexDoc": {
                        "dataProperties": [
                            {
                                "sourceProperty": "http://xmlns.com/foaf/0.1/givenName",
                                "targetProperty": "givenName",
                                "isFunctional": "true"
                            },
                            {
                                "sourceProperty": "http://xmlns.com/foaf/0.1/familyName",
                                "targetProperty": "familyNname",
                                "isFunctional": "true"
                            }				 	 
                        ]
                    }
                },

                "http://xmlns.com/foaf/0.1/Organization": {
                    "type": "organization",
                    "idProperty": "http://data.hulib.helsinki.fi/schemas/uhod/v1/hasCanonicalURI",			

                    "indexDoc": {			
                        "dataProperties": [
                            {
                                "sourceProperty": "http://purl.org/dc/terms/title",
                                "targetProperty": "title",
                                "isFunctional": "true"
                            }		 	 
                        ]
                    }
                }	
            }
        }
    ]
}
